werkflow_aws/__init__.py
werkflow_aws/authorization_type.py
werkflow_aws/aws.py
werkflow_aws/supported_clients.py
werkflow_aws/exceptions/__init__.py
werkflow_aws/exceptions/empty_response_exception.py
werkflow_aws/exceptions/unset_aws_connection_exception.py
werkflow_aws/helpers/__init__.py
werkflow_aws/helpers/collect_paginator.py
werkflow_aws/models/__init__.py
werkflow_aws/models/aws_credentials_set.py
werkflow_aws/models/aws_region.py
werkflow_aws/models/aws_services.py
werkflow_aws/models/athena/__init__.py
werkflow_aws/models/athena/athena_acl_configuration.py
werkflow_aws/models/athena/athena_calculation_configuration.py
werkflow_aws/models/athena/athena_calculation_result.py
werkflow_aws/models/athena/athena_calculation_state.py
werkflow_aws/models/athena/athena_calculation_statistics.py
werkflow_aws/models/athena/athena_calculation_status.py
werkflow_aws/models/athena/athena_column_info.py
werkflow_aws/models/athena/athena_column_nullable.py
werkflow_aws/models/athena/athena_connection_type.py
werkflow_aws/models/athena/athena_create_data_catalog_request.py
werkflow_aws/models/athena/athena_create_data_catalog_response.py
werkflow_aws/models/athena/athena_create_named_query_request.py
werkflow_aws/models/athena/athena_create_named_query_response.py
werkflow_aws/models/athena/athena_create_prepared_statement_request.py
werkflow_aws/models/athena/athena_create_prepared_statement_response.py
werkflow_aws/models/athena/athena_data_catalog.py
werkflow_aws/models/athena/athena_data_catalog_status.py
werkflow_aws/models/athena/athena_data_catalog_summary.py
werkflow_aws/models/athena/athena_data_catalog_type.py
werkflow_aws/models/athena/athena_database.py
werkflow_aws/models/athena/athena_delete_data_catalog_request.py
werkflow_aws/models/athena/athena_delete_data_catalog_response.py
werkflow_aws/models/athena/athena_delete_named_query_request.py
werkflow_aws/models/athena/athena_delete_named_query_response.py
werkflow_aws-0.6.0.dist-info/licenses/LICENSE
werkflow_aws-0.6.0.dist-info/METADATA
werkflow_aws-0.6.0.dist-info/WHEEL
werkflow_aws-0.6.0.dist-info/top_level.txt
werkflow_aws-0.6.0.dist-info/RECORD
