Metadata-Version: 2.4
Name: werkflow-aws
Version: 0.6.0
Summary: An AWS module for Werkflow powered by Boto3.
Author-email: Ada Lundhe <adalundhe@lundhe.audio>
Keywords: pypi,cicd,python,werkflow,workflow,werkflow-core,aws,boto3,aws-cli
Classifier: Programming Language :: Python :: 3.11
Classifier: Programming Language :: Python :: 3.12
Classifier: Programming Language :: Python :: 3.13
Classifier: Operating System :: OS Independent
Requires-Python: >=3.11
License-File: LICENSE
Requires-Dist: werkflow-core
Requires-Dist: werkflow-file
Requires-Dist: werkflow-secrets
Requires-Dist: werkflow-shell
Requires-Dist: werkflow-system
Requires-Dist: boto3
Requires-Dist: pydantic
Dynamic: license-file
